LICENSE
py3status_cpu_governor/__init__.py
py3status_cpu_governor/cpu_governor.py
py3status_cpu_governor-0.1.3.dist-info/entry_points.txt
py3status_cpu_governor-0.1.3.dist-info/LICENSE
py3status_cpu_governor-0.1.3.dist-info/WHEEL
py3status_cpu_governor-0.1.3.dist-info/METADATA
py3status_cpu_governor-0.1.3.dist-info/RECORD
