Metadata-Version: 2.1
Name: py3status-cpu-governor
Version: 0.1.3
Summary: py3status monitor to show the state of your cpu governor
Home-page: https://github.com/mcgillij/py3status-cpu-governor
License: MIT
Keywords: cpu,governor,py3status,i3,monitor
Author: mcgillij
Author-email: mcgillivray.jason@gmail.com
Requires-Python: >=3.9,<4.0
Classifier: Environment :: X11 Applications
Classifier: Intended Audience :: End Users/Desktop
Classifier: License :: OSI Approved :: MIT License
Classifier: Operating System :: POSIX :: Linux
Classifier: Programming Language :: Python :: 3
Classifier: Programming Language :: Python :: 3.10
Classifier: Programming Language :: Python :: 3.9
Classifier: Topic :: Desktop Environment :: Window Managers
Classifier: Topic :: System :: Hardware
Classifier: Topic :: System :: Monitoring
Requires-Dist: py3status (>=3.34,<4.0)
Project-URL: Documentation, https://github.com/mcgillij/py3status-cpu-governor
Project-URL: Repository, https://github.com/mcgillij/py3status-cpu-governor
